pyminifier/__init__.py
pyminifier/__main__.py
pyminifier/analyze.py
pyminifier/compression.py
pyminifier/minification.py
pyminifier/obfuscate.py
pyminifier/token_utils.py
pyminifier/__pycache__/__init__.cpython-310.opt-1.pyc
pyminifier/__pycache__/__main__.cpython-310.opt-1.pyc
pyminifier/__pycache__/analyze.cpython-310.opt-1.pyc
pyminifier/__pycache__/compression.cpython-310.opt-1.pyc
pyminifier/__pycache__/minification.cpython-310.opt-1.pyc
pyminifier/__pycache__/obfuscate.cpython-310.opt-1.pyc
pyminifier/__pycache__/token_utils.cpython-310.opt-1.pyc
pyminifier3-2.3.3.dist-info/LICENSE
pyminifier3-2.3.3.dist-info/METADATA
pyminifier3-2.3.3.dist-info/WHEEL
pyminifier3-2.3.3.dist-info/entry_points.txt
pyminifier3-2.3.3.dist-info/top_level.txt
pyminifier3-2.3.3.dist-info/RECORD
